  0           0 RESUME                   0

  1           2 LOAD_CONST               0 (0)
              4 LOAD_CONST               1 (None)
              6 IMPORT_NAME              0 (logging)
              8 STORE_NAME               0 (logging)

  2          10 LOAD_CONST               0 (0)
             12 LOAD_CONST               1 (None)
             14 IMPORT_NAME              1 (threading)
             16 STORE_NAME               1 (threading)

  3          18 LOAD_CONST               0 (0)
             20 LOAD_CONST               1 (None)
             22 IMPORT_NAME              2 (time)
             24 STORE_NAME               2 (time)

  5          26 LOAD_CONST               2 (<code object thread_function at 0x0000020ACA028AB0, file "test.py", line 5>)
             28 MAKE_FUNCTION            0
             30 STORE_NAME               3 (thread_function)

 10          32 LOAD_NAME                4 (__name__)
             34 LOAD_CONST               3 ('__main__')
             36 COMPARE_OP              40 (==)
             40 POP_JUMP_IF_FALSE      197 (to 436)

 11          42 LOAD_CONST               4 ('%(asctime)s: %(message)s')
             44 STORE_NAME               5 (format)

 12          46 PUSH_NULL
             48 LOAD_NAME                0 (logging)
             50 LOAD_ATTR               12 (basicConfig)
             70 LOAD_NAME                5 (format)
             72 LOAD_NAME                0 (logging)
             74 LOAD_ATTR               14 (INFO)

 13          94 LOAD_CONST               5 ('%H:%M:%S')

 12          96 KW_NAMES                 6 (('format', 'level', 'datefmt'))
             98 CALL                     3
            106 POP_TOP

 15         108 PUSH_NULL
            110 LOAD_NAME                8 (list)
            112 CALL                     0
            120 STORE_NAME               9 (threads)

 16         122 PUSH_NULL
            124 LOAD_NAME               10 (range)
            126 LOAD_CONST               7 (3)
            128 CALL                     1
            136 GET_ITER
        >>  138 FOR_ITER                75 (to 292)
            142 STORE_NAME              11 (index)

 17         144 PUSH_NULL
            146 LOAD_NAME                0 (logging)
            148 LOAD_ATTR               24 (info)
            168 LOAD_CONST               8 ('Main    : create and start thread %d.')
            170 LOAD_NAME               11 (index)
            172 CALL                     2
            180 POP_TOP

 18         182 PUSH_NULL
            184 LOAD_NAME                1 (threading)
            186 LOAD_ATTR               26 (Thread)
            206 LOAD_NAME                3 (thread_function)
            208 LOAD_NAME               11 (index)
            210 BUILD_TUPLE              1
            212 KW_NAMES                 9 (('target', 'args'))
            214 CALL                     2
            222 STORE_NAME              14 (x)

 19         224 LOAD_NAME                9 (threads)
            226 LOAD_ATTR               31 (NULL|self + append)
            246 LOAD_NAME               14 (x)
            248 CALL                     1
            256 POP_TOP

 20         258 LOAD_NAME               14 (x)
            260 LOAD_ATTR               33 (NULL|self + start)
            280 CALL                     0
            288 POP_TOP
            290 JUMP_BACKWARD           77 (to 138)

 16     >>  292 END_FOR

 22         294 PUSH_NULL
            296 LOAD_NAME               17 (enumerate)
            298 LOAD_NAME                9 (threads)
            300 CALL                     1
            308 GET_ITER
        >>  310 FOR_ITER                59 (to 432)
            314 UNPACK_SEQUENCE          2
            318 STORE_NAME              11 (index)
            320 STORE_NAME              18 (thread)

 23         322 PUSH_NULL
            324 LOAD_NAME                0 (logging)
            326 LOAD_ATTR               24 (info)
            346 LOAD_CONST              10 ('Main    : before joining thread %d.')
            348 LOAD_NAME               11 (index)
            350 CALL                     2
            358 POP_TOP

 24         360 LOAD_NAME               18 (thread)
            362 LOAD_ATTR               39 (NULL|self + join)
            382 CALL                     0
            390 POP_TOP

 25         392 PUSH_NULL
            394 LOAD_NAME                0 (logging)
            396 LOAD_ATTR               24 (info)
            416 LOAD_CONST              11 ('Main    : thread %d done')
            418 LOAD_NAME               11 (index)
            420 CALL                     2
            428 POP_TOP
            430 JUMP_BACKWARD           61 (to 310)

 22     >>  432 END_FOR
            434 RETURN_CONST             1 (None)

 10     >>  436 RETURN_CONST             1 (None)

Disassembly of <code object thread_function at 0x0000020ACA028AB0, file "test.py", line 5>:
  5           0 RESUME                   0

  6           2 LOAD_GLOBAL              1 (NULL + logging)
             12 LOAD_ATTR                2 (info)
             32 LOAD_CONST               1 ('Thread %s: starting')
             34 LOAD_FAST                0 (name)
             36 CALL                     2
             44 POP_TOP

  7          46 LOAD_GLOBAL              5 (NULL + time)
             56 LOAD_ATTR                6 (sleep)
             76 LOAD_CONST               2 (2)
             78 CALL                     1
             86 POP_TOP

  8          88 LOAD_GLOBAL              1 (NULL + logging)
             98 LOAD_ATTR                2 (info)
            118 LOAD_CONST               3 ('Thread %s: finishing')
            120 LOAD_FAST                0 (name)
            122 CALL                     2
            130 POP_TOP
            132 RETURN_CONST             0 (None)
